videodl/__init__.py
videodl/videodl.py
videodl/modules/__init__.py
videodl/modules/grabber.py
videodl/modules/cdm/charlespikachu_plusfifa.wvd
videodl/modules/cdm/charlespikachu_wittytv.wvd
videodl/modules/common/__init__.py
videodl/modules/common/anyfetcher.py
videodl/modules/common/bugpk.py
videodl/modules/common/bv.py
videodl/modules/common/gvvip.py
videodl/modules/common/iiilab.py
videodl/modules/common/im1907.py
videodl/modules/common/kedou.py
videodl/modules/common/kit9.py
videodl/modules/common/kukutool.py
videodl/modules/common/longzhu.py
videodl/modules/common/lvlong.py
videodl/modules/common/mizhi.py
videodl/modules/common/nologo.py
videodl/modules/common/odown.py
videodl/modules/common/pv.py
videodl/modules/common/qingting.py
videodl/modules/common/qzxdptools.py
videodl/modules/common/ray.py
videodl/modules/common/senjiexi.py
videodl/modules/common/snapany.py
videodl/modules/common/snapwc.py
videodl/modules/common/vget.py
videodl/modules/common/videofk.py
videodl/modules/common/xcvts.py
videodl/modules/common/xiazaitool.py
videodl/modules/common/xmflv.py
videodl/modules/common/xzdx.py
videodl/modules/common/zanqianba.py
videodl/modules/js/__init__.py
videodl/modules/js/cctv/__init__.py
videodl/modules/js/cctv/cctv_wasm.js
videodl/modules/js/cctv/decrypt.js
videodl/modules/js/tencent/__init__.py
videodl/modules/js/tencent/ckey.wasm
videodl/modules/js/tencent/vqq_ckey-8.1.js
videodl/modules/js/tencent/vqq_ckey-8.5.js
videodl/modules/js/tencent/vqq_ckey-9.1.js
videodl/modules/js/xmflv/__init__.py
videodl/modules/js/xmflv/xiami_logic_ref.js
videodl/modules/js/xmflv/xiami_token.wasm
videodl/modules/js/youtube/__init__.py
videodl/modules/js/youtube/botguard.js
videodl/modules/js/youtube/jsinterp.py
videodl/modules/js/youtube/runner.js
videodl/modules/sources/__init__.py
videodl/modules/sources/acfun.py
videodl/modules/sources/artetv.py
videodl/modules/sources/baidutieba.py
videodl/modules/sources/base.py
videodl/modules/sources/bilibili.py
videofetch-0.6.3.dist-info/LICENSE
videofetch-0.6.3.dist-info/METADATA
videofetch-0.6.3.dist-info/WHEEL
videofetch-0.6.3.dist-info/entry_points.txt
videofetch-0.6.3.dist-info/top_level.txt
videofetch-0.6.3.dist-info/zip-safe
videofetch-0.6.3.dist-info/RECORD
