Metadata-Version: 2.1
Name: videofetch
Version: 0.6.3
Summary: Videodl: A lightweight video downloader written in pure python
Home-page: https://github.com/CharlesPikachu/videodl
Author: Zhenchao Jin
Author-email: charlesblwx@gmail.com
License: PolyForm-Noncommercial-1.0.0
Classifier: License :: Free for non-commercial use
Classifier: Programming Language :: Python :: 3
Classifier: Intended Audience :: Developers
Classifier: Operating System :: OS Independent
License-File: LICENSE
Requires-Dist: requests
Requires-Dist: rich
Requires-Dist: prettytable
Requires-Dist: click
Requires-Dist: json-repair
Requires-Dist: pathvalidate
Requires-Dist: platformdirs
Requires-Dist: emoji
Requires-Dist: bleach
Requires-Dist: beautifulsoup4
Requires-Dist: parsel
Requires-Dist: tqdm
Requires-Dist: pycryptodomex
Requires-Dist: pycryptodome
Requires-Dist: cryptography
Requires-Dist: tldextract
Requires-Dist: fake-useragent
Requires-Dist: nodejs-wheel
Requires-Dist: pyfreeproxy
Requires-Dist: playwright
Requires-Dist: questionary
Requires-Dist: pywidevine
Requires-Dist: curl-cffi
Requires-Dist: m3u8
